{
  "generated_at": "2026-06-06T02:38:07.512172+00:00",
  "date": "2026-06-05",
  "bookmaker": "bet365",
  "total_games": 0,
  "total_value_bets": 0,
  "signals": [],
  "value_bets": [],
  "props_analysis": [],
  "nba_analysis": [],
  "mlb_analysis": [
    {
      "home_team": "Houston Astros",
      "away_team": "Athletics",
      "bets": [
        {
          "player": "Lance McCullers Jr.",
          "team": "Houston Astros",
          "opponent": "Athletics",
          "player_type": "pitcher",
          "market": "Retraits au baton Over 4.0",
          "stat_key": "strikeouts",
          "line": 4.0,
          "season_avg": 5.0,
          "adj_proj": 5.0,
          "opp_k_rate": 21.5,
          "park_factor": 0.97,
          "our_prob": 61.9,
          "edge_pct": 17.6,
          "kelly": 5.0,
          "est_odds": 1.909,
          "dk_implied": 52.6,
          "context": [
            "Terrain: Neutre (PF 0.97)"
          ]
        }
      ],
      "commence_time": "2026-06-06T00:11:00Z"
    },
    {
      "home_team": "Texas Rangers",
      "away_team": "Cleveland Guardians",
      "bets": [
        {
          "player": "Parker Messick",
          "team": "Cleveland Guardians",
          "opponent": "Texas Rangers",
          "player_type": "pitcher",
          "market": "Retraits au baton Over 5.0",
          "stat_key": "strikeouts",
          "line": 5.0,
          "season_avg": 5.67,
          "adj_proj": 5.91,
          "opp_k_rate": 22.4,
          "park_factor": 1.05,
          "our_prob": 58.3,
          "edge_pct": 10.8,
          "kelly": 3.1,
          "est_odds": 1.909,
          "dk_implied": 52.6,
          "context": [
            "Terrain: Favorable frappeurs (PF 1.05)"
          ]
        }
      ],
      "commence_time": "2026-06-06T00:16:00Z"
    },
    {
      "home_team": "Detroit Tigers",
      "away_team": "Seattle Mariners",
      "bets": [
        {
          "player": "Bryan Woo",
          "team": "Seattle Mariners",
          "opponent": "Detroit Tigers",
          "player_type": "pitcher",
          "market": "Retraits au baton Over 6.0",
          "stat_key": "strikeouts",
          "line": 6.0,
          "season_avg": 7.8,
          "adj_proj": 7.84,
          "opp_k_rate": 21.6,
          "park_factor": 0.99,
          "our_prob": 69.8,
          "edge_pct": 32.6,
          "kelly": 9.1,
          "est_odds": 1.909,
          "dk_implied": 52.6,
          "context": [
            "Terrain: Neutre (PF 0.99)"
          ],
          "status": "started"
        }
      ],
      "commence_time": "2026-06-05T22:41:00Z",
      "status": "started"
    },
    {
      "home_team": "Toronto Blue Jays",
      "away_team": "Baltimore Orioles",
      "bets": [
        {
          "player": "B. Young",
          "team": "Baltimore Orioles",
          "opponent": "Toronto Blue Jays",
          "player_type": "pitcher",
          "market": "Retraits au baton Over 4.0",
          "stat_key": "strikeouts",
          "line": 4.0,
          "season_avg": 5.5,
          "adj_proj": 5.5,
          "opp_k_rate": 21.5,
          "park_factor": 1.0,
          "our_prob": 70.9,
          "edge_pct": 34.7,
          "kelly": 9.7,
          "est_odds": 1.909,
          "dk_implied": 52.6,
          "context": [],
          "status": "started"
        },
        {
          "player": "Gunnar Henderson",
          "team": "Baltimore Orioles",
          "opponent": "Toronto Blue Jays",
          "player_type": "batter",
          "market": "Buts totaux Over 1.5",
          "stat_key": "total_bases",
          "line": 1.5,
          "season_avg": 1.867,
          "adj_proj": 2.016,
          "opp_k_rate": null,
          "opp_pitcher": "Trey Yesavage",
          "opp_pitcher_k": 6.5,
          "platoon": "Platoon avantageux (L vs R)",
          "park_factor": 1.0,
          "our_prob": 50.5,
          "edge_pct": 11.7,
          "kelly": 2.4,
          "est_odds": 2.21,
          "dk_implied": 45.2,
          "context": [
            "vs Trey Yesavage (6.5 K/dep) — Moyen",
            "Platoon avantageux (L vs R)",
            "Confirmer lineup avant de parier"
          ],
          "status": "started"
        }
      ],
      "commence_time": "2026-06-05T23:08:00Z",
      "status": "started"
    },
    {
      "home_team": "Miami Marlins",
      "away_team": "Tampa Bay Rays",
      "bets": [
        {
          "player": "Drew Rasmussen",
          "team": "Tampa Bay Rays",
          "opponent": "Miami Marlins",
          "player_type": "pitcher",
          "market": "Retraits au baton Over 4.5",
          "stat_key": "strikeouts",
          "line": 4.5,
          "season_avg": 5.4,
          "adj_proj": 5.73,
          "opp_k_rate": 22.8,
          "park_factor": 0.95,
          "our_prob": 65.0,
          "edge_pct": 23.5,
          "kelly": 6.6,
          "est_odds": 1.909,
          "dk_implied": 52.6,
          "context": [
            "Terrain: Favorable lanceurs (PF 0.95)"
          ],
          "status": "started"
        }
      ],
      "commence_time": "2026-06-05T23:11:00Z",
      "status": "started"
    },
    {
      "home_team": "Atlanta Braves",
      "away_team": "Pittsburgh Pirates",
      "bets": [
        {
          "player": "Matt Olson",
          "team": "Atlanta Braves",
          "opponent": "Pittsburgh Pirates",
          "player_type": "batter",
          "market": "Buts totaux Over 1.5",
          "stat_key": "total_bases",
          "line": 1.5,
          "season_avg": 1.867,
          "adj_proj": 2.138,
          "opp_k_rate": null,
          "opp_pitcher": "Mitch Keller",
          "opp_pitcher_k": 4.5,
          "platoon": "Platoon avantageux (L vs R)",
          "park_factor": 1.02,
          "our_prob": 54.4,
          "edge_pct": 14.3,
          "kelly": 3.2,
          "est_odds": 2.1,
          "dk_implied": 47.6,
          "context": [
            "vs Mitch Keller (4.5 K/dep) — Contact",
            "Platoon avantageux (L vs R)",
            "Terrain: Neutre (PF 1.02)",
            "Confirmer lineup avant de parier"
          ],
          "status": "started"
        }
      ],
      "commence_time": "2026-06-05T23:16:00Z",
      "status": "started"
    },
    {
      "home_team": "Minnesota Twins",
      "away_team": "Kansas City Royals",
      "bets": [
        {
          "player": "Michael Wacha",
          "team": "Kansas City Royals",
          "opponent": "Minnesota Twins",
          "player_type": "pitcher",
          "market": "Retraits au baton Over 4.5",
          "stat_key": "strikeouts",
          "line": 4.5,
          "season_avg": 5.33,
          "adj_proj": 5.28,
          "opp_k_rate": 21.3,
          "park_factor": 0.99,
          "our_prob": 56.4,
          "edge_pct": 7.2,
          "kelly": 2.1,
          "est_odds": 1.909,
          "dk_implied": 52.6,
          "context": [
            "Terrain: Neutre (PF 0.99)"
          ],
          "status": "started"
        }
      ],
      "commence_time": "2026-06-06T00:16:00Z",
      "status": "started"
    }
  ],
  "ai_analysis": {}
}