{
  "generated_at": "2026-06-07T13:28:45.244046+00:00",
  "date": "2026-06-07",
  "bookmaker": "bet365",
  "total_games": 0,
  "total_value_bets": 0,
  "signals": [],
  "value_bets": [],
  "props_analysis": [],
  "nba_analysis": [],
  "mlb_analysis": [
    {
      "home_team": "Atlanta Braves",
      "away_team": "Pittsburgh Pirates",
      "bets": [
        {
          "player": "Bryce Elder",
          "team": "Atlanta Braves",
          "opponent": "Pittsburgh Pirates",
          "player_type": "pitcher",
          "market": "Retraits au baton Over 4.5",
          "stat_key": "strikeouts",
          "line": 4.5,
          "season_avg": 5.17,
          "adj_proj": 5.77,
          "opp_k_rate": 24.0,
          "park_factor": 1.02,
          "our_prob": 65.7,
          "edge_pct": 24.8,
          "kelly": 7.0,
          "est_odds": 1.909,
          "dk_implied": 52.6,
          "context": [
            "Adversaire K%: 24.0% (favorable)",
            "Terrain: Neutre (PF 1.02)"
          ]
        },
        {
          "player": "Matt Olson",
          "team": "Atlanta Braves",
          "opponent": "Pittsburgh Pirates",
          "player_type": "batter",
          "market": "Buts totaux Over 1.5",
          "stat_key": "total_bases",
          "line": 1.5,
          "season_avg": 1.8,
          "adj_proj": 2.062,
          "opp_k_rate": null,
          "opp_pitcher": "Bubba Chandler",
          "opp_pitcher_k": 4.5,
          "platoon": "Platoon avantageux (L vs R)",
          "park_factor": 1.02,
          "our_prob": 52.1,
          "edge_pct": 14.5,
          "kelly": 3.0,
          "est_odds": 2.2,
          "dk_implied": 45.5,
          "context": [
            "vs Bubba Chandler (4.5 K/dep) — Contact",
            "Platoon avantageux (L vs R)",
            "Terrain: Neutre (PF 1.02)",
            "Confirmer lineup avant de parier"
          ]
        }
      ],
      "commence_time": "2026-06-07T17:36:00Z"
    },
    {
      "home_team": "Philadelphia Phillies",
      "away_team": "Chicago White Sox",
      "bets": [
        {
          "player": "Aaron Nola",
          "team": "Philadelphia Phillies",
          "opponent": "Chicago White Sox",
          "player_type": "pitcher",
          "market": "Retraits au baton Over 4.0",
          "stat_key": "strikeouts",
          "line": 4.0,
          "season_avg": 5.4,
          "adj_proj": 5.48,
          "opp_k_rate": 21.8,
          "park_factor": 1.0,
          "our_prob": 70.6,
          "edge_pct": 34.1,
          "kelly": 9.6,
          "est_odds": 1.909,
          "dk_implied": 52.6,
          "context": []
        }
      ],
      "commence_time": "2026-06-07T17:36:00Z"
    },
    {
      "home_team": "Toronto Blue Jays",
      "away_team": "Baltimore Orioles",
      "bets": [
        {
          "player": "Shane Baz",
          "team": "Baltimore Orioles",
          "opponent": "Toronto Blue Jays",
          "player_type": "pitcher",
          "market": "Retraits au baton Over 4.5",
          "stat_key": "strikeouts",
          "line": 4.5,
          "season_avg": 5.67,
          "adj_proj": 5.67,
          "opp_k_rate": 21.5,
          "park_factor": 1.0,
          "our_prob": 64.0,
          "edge_pct": 21.6,
          "kelly": 6.1,
          "est_odds": 1.909,
          "dk_implied": 52.6,
          "context": []
        },
        {
          "player": "Gunnar Henderson",
          "team": "Baltimore Orioles",
          "opponent": "Toronto Blue Jays",
          "player_type": "batter",
          "market": "Buts totaux Over 1.5",
          "stat_key": "total_bases",
          "line": 1.5,
          "season_avg": 1.867,
          "adj_proj": 2.016,
          "opp_k_rate": null,
          "opp_pitcher": "Kevin Gausman",
          "opp_pitcher_k": 6.5,
          "platoon": "Platoon avantageux (L vs R)",
          "park_factor": 1.0,
          "our_prob": 50.5,
          "edge_pct": 14.3,
          "kelly": 2.8,
          "est_odds": 2.26,
          "dk_implied": 44.2,
          "context": [
            "vs Kevin Gausman (6.5 K/dep) — Moyen",
            "Platoon avantageux (L vs R)",
            "Confirmer lineup avant de parier"
          ]
        }
      ],
      "commence_time": "2026-06-07T17:38:00Z"
    },
    {
      "home_team": "Detroit Tigers",
      "away_team": "Seattle Mariners",
      "bets": [
        {
          "player": "Jack Flaherty",
          "team": "Detroit Tigers",
          "opponent": "Seattle Mariners",
          "player_type": "pitcher",
          "market": "Retraits au baton Over 5.5",
          "stat_key": "strikeouts",
          "line": 5.5,
          "season_avg": 7.2,
          "adj_proj": 6.9,
          "opp_k_rate": 20.6,
          "park_factor": 0.99,
          "our_prob": 65.4,
          "edge_pct": 24.3,
          "kelly": 6.8,
          "est_odds": 1.909,
          "dk_implied": 52.6,
          "context": [
            "Terrain: Neutre (PF 0.99)"
          ]
        }
      ],
      "commence_time": "2026-06-07T17:41:00Z"
    },
    {
      "home_team": "Minnesota Twins",
      "away_team": "Kansas City Royals",
      "bets": [
        {
          "player": "Noah Cameron",
          "team": "Kansas City Royals",
          "opponent": "Minnesota Twins",
          "player_type": "pitcher",
          "market": "Retraits au baton Over 4.5",
          "stat_key": "strikeouts",
          "line": 4.5,
          "season_avg": 5.5,
          "adj_proj": 5.45,
          "opp_k_rate": 21.3,
          "park_factor": 0.99,
          "our_prob": 59.9,
          "edge_pct": 13.8,
          "kelly": 3.9,
          "est_odds": 1.909,
          "dk_implied": 52.6,
          "context": [
            "Terrain: Neutre (PF 0.99)"
          ]
        }
      ],
      "commence_time": "2026-06-07T18:11:00Z"
    }
  ],
  "ai_analysis": {}
}